qadapt/__init__.py
qadapt/driver.py
qadapt/qadapt.py
qadapt-1.2.0.dist-info/METADATA
qadapt-1.2.0.dist-info/WHEEL
qadapt-1.2.0.dist-info/top_level.txt
qadapt-1.2.0.dist-info/RECORD
